{
  "collected_at": "2026-05-11T10:54:01Z",
  "project": "aiter",
  "repo": "ROCm/aiter",
  "pr_velocity": {
    "this_week": {
      "opened": 108,
      "merged": 64,
      "closed": 24
    },
    "last_week": {
      "opened": 90,
      "merged": 51,
      "closed": 24
    },
    "median_time_to_merge_hours": 23.0,
    "merge_count": 116,
    "stale_prs": 101
  },
  "contributors": {
    "active_this_week": 87,
    "total_contributors": 176,
    "top_contributors": [
      {
        "author": "sunway513",
        "prs_submitted": 20,
        "prs_merged": 7,
        "commits": 11
      },
      {
        "author": "gyohuangxin",
        "prs_submitted": 18,
        "prs_merged": 11,
        "commits": 39
      },
      {
        "author": "yzhou103",
        "prs_submitted": 9,
        "prs_merged": 4,
        "commits": 12
      },
      {
        "author": "ChuanLi1101",
        "prs_submitted": 9,
        "prs_merged": 1,
        "commits": 0
      },
      {
        "author": "zufayu",
        "prs_submitted": 8,
        "prs_merged": 0,
        "commits": 0
      },
      {
        "author": "ganyi1996ppo",
        "prs_submitted": 7,
        "prs_merged": 1,
        "commits": 4
      },
      {
        "author": "amd-ruitang3",
        "prs_submitted": 7,
        "prs_merged": 3,
        "commits": 6
      },
      {
        "author": "k50112113",
        "prs_submitted": 6,
        "prs_merged": 1,
        "commits": 1
      },
      {
        "author": "Boss2002n",
        "prs_submitted": 6,
        "prs_merged": 0,
        "commits": 0
      },
      {
        "author": "peymanr",
        "prs_submitted": 6,
        "prs_merged": 0,
        "commits": 0
      }
    ],
    "bus_factor": 8
  },
  "issue_health": {
    "total_open": 172,
    "opened_this_week": 4,
    "closed_this_week": 3,
    "unanswered": 65
  },
  "ci_health": null,
  "ci_signal_time": null,
  "release_cadence": {
    "days_since_last": 1.6,
    "avg_interval_days": 4.0,
    "total_releases": 5,
    "latest_tag": "v0.1.13"
  }
}