{
  "collected_at": "2026-07-12T09:40:41Z",
  "releases": [
    {
      "tag_name": "jax-v0.10.2",
      "name": "JAX v0.10.2",
      "published_at": "2026-06-17T23:39:56Z",
      "html_url": "https://github.com/jax-ml/jax/releases/tag/jax-v0.10.2",
      "prerelease": false
    },
    {
      "tag_name": "jax-v0.10.1",
      "name": "JAX v0.10.1",
      "published_at": "2026-05-20T15:07:07Z",
      "html_url": "https://github.com/jax-ml/jax/releases/tag/jax-v0.10.1",
      "prerelease": false
    },
    {
      "tag_name": "jax-v0.10.0",
      "name": "JAX v0.10.0",
      "published_at": "2026-04-16T13:09:00Z",
      "html_url": "https://github.com/jax-ml/jax/releases/tag/jax-v0.10.0",
      "prerelease": false
    },
    {
      "tag_name": "jax-v0.9.2",
      "name": "JAX v0.9.2",
      "published_at": "2026-03-18T23:40:31Z",
      "html_url": "https://github.com/jax-ml/jax/releases/tag/jax-v0.9.2",
      "prerelease": false
    },
    {
      "tag_name": "jax-v0.9.1",
      "name": "JAX v0.9.1",
      "published_at": "2026-03-02T11:13:44Z",
      "html_url": "https://github.com/jax-ml/jax/releases/tag/jax-v0.9.1",
      "prerelease": false
    }
  ]
}